gac/__init__.py
gac/config.py
gac/main.py
itwingstestsprojectn-0.1.dist-info/LICENSE
itwingstestsprojectn-0.1.dist-info/METADATA
itwingstestsprojectn-0.1.dist-info/WHEEL
itwingstestsprojectn-0.1.dist-info/top_level.txt
itwingstestsprojectn-0.1.dist-info/RECORD
